
[
    {

        "id":1,
        "name": "Towel Cum Blanket",
        "price":154,
        "image":"https://bornbabies.com/cdn/shop/files/2_90463cba-aa3f-461e-8524-622530e7c7ea.jpg?v=1714214501&width=990",
        "quantity":1


    },
    {
        "id":2,
        "name": " Cradle With Mosquito Protection Net",
        "price":194,
        "image":"https://bornbabies.com/cdn/shop/files/01_37560684-ee4b-4f6f-8280-76acf825a59c.jpg?v=1711971516&width=713",
        "quantity":1
    },
    {
        "id":3,
        "name": " Top & Shorts Set ",
        "price":161,
        "image":"https://bornbabies.com/cdn/shop/files/1_74f8a9bf-251c-4652-9bec-b8449fbd54be.jpg?v=1709968229&width=713",
        "quantity":1
    },
    {
        "id":4,
        "name": "Silicone Nipple & Travel Cap ",
        "price":145,
        "image":"https://bornbabies.com/cdn/shop/files/1_3a401de3-f3b0-4201-a076-0eb6d5d877d9.jpg?v=1711968447&width=713",
        "quantity":1
    },
    {
        "id":5,
        "name": " Bed Set Cum Sleeping Bag ",
        "price":199,
        "image":"https://bornbabies.com/cdn/shop/files/1_22be7ea7-6d0b-49db-acc2-a660c72772d1.jpg?v=1706342622&width=713",
        "quantity":1
    },
    {
        "id":6,
        "name": "Knot Frock-Multicolor",
        "price":178,
        "image":"https://bornbabies.com/cdn/shop/files/1_34e66d8c-5fa0-4d02-b050-aeceb3c81869.jpg?v=1712051422&width=713",
        "quantity":1
    }

    
]